<?xml version="1.0" encoding="UTF-8" ?>        
        <XML>
            <Content>UPDATE</Content>
            <Clip>
                <ClipName>DOCUHIS0005</ClipName>
                <TipoContenido>DOCUMENTALES</TipoContenido>
                <Contenido><![CDATA[ INVASION ESTADOUNIDENSE A PANAMA: OPERACION CAUSA JUSTA]]></Contenido>
                <OriginalTitle></OriginalTitle>
                <Description> </Description>
                <Notes>a</Notes>
                <DurPrev></DurPrev>
                <Chapter></Chapter>
                <EndDate></EndDate>
                <EPG></EPG>
                <EPG_Content> </EPG_Content>
                <Segments>
            
                <Segment>
                    <SegTitle>1-4 HISTORICOS - INVASION ESTADOUNIDENSE A PANAMA: OPERACION CAUSA JUSTA</SegTitle>
                    <MediaID>DOCUHIS000501</MediaID>
                    <Duration>00:10:50.00</Duration>
                    <SegNumber>1</SegNumber>
                    <ClipGroup>PROGRAMA</ClipGroup>
                    <Description> </Description>
                </Segment>
            
                <Segment>
                    <SegTitle>2-4 HISTORICOS - INVASION ESTADOUNIDENSE A PANAMA: OPERACION CAUSA JUSTA</SegTitle>
                    <MediaID>DOCUHIS000502</MediaID>
                    <Duration>00:09:39.00</Duration>
                    <SegNumber>2</SegNumber>
                    <ClipGroup>PROGRAMA</ClipGroup>
                    <Description> </Description>
                </Segment>
            
                <Segment>
                    <SegTitle>3-4 HISTORICOS - INVASION ESTADOUNIDENSE A PANAMA: OPERACION CAUSA JUSTA</SegTitle>
                    <MediaID>DOCUHIS000503</MediaID>
                    <Duration>00:15:37.00</Duration>
                    <SegNumber>3</SegNumber>
                    <ClipGroup>PROGRAMA</ClipGroup>
                    <Description> </Description>
                </Segment>
            
                <Segment>
                    <SegTitle>4-4 HISTORICOS - INVASION ESTADOUNIDENSE A PANAMA: OPERACION CAUSA JUSTA</SegTitle>
                    <MediaID>DOCUHIS000504</MediaID>
                    <Duration>00:16:00.00</Duration>
                    <SegNumber>4</SegNumber>
                    <ClipGroup>PROGRAMA</ClipGroup>
                    <Description> </Description>
                </Segment>
            </Segments></Clip></XML>