<?xml version="1.0" encoding="UTF-8" ?>        
        <XML>
            <Content>UPDATE</Content>
            <Clip>
                <ClipName>INPRREA0062</ClipName>
                <TipoContenido>INFORMATIVOS PROGRAMAS</TipoContenido>
                <Contenido><![CDATA[ PROG 016]]></Contenido>
                <OriginalTitle></OriginalTitle>
                <Description> </Description>
                <Notes>a</Notes>
                <DurPrev></DurPrev>
                <Chapter></Chapter>
                <EndDate></EndDate>
                <EPG></EPG>
                <EPG_Content> </EPG_Content>
                <Segments>
            
                <Segment>
                    <SegTitle>1-2 REALIDADES - PROG 016</SegTitle>
                    <MediaID>INPRREA006201</MediaID>
                    <Duration>00:15:42.00</Duration>
                    <SegNumber>1</SegNumber>
                    <ClipGroup>PROGRAMA</ClipGroup>
                    <Description> </Description>
                </Segment>
            
                <Segment>
                    <SegTitle>2-2 REALIDADES - PROG 016</SegTitle>
                    <MediaID>INPRREA006202</MediaID>
                    <Duration>00:10:03.00</Duration>
                    <SegNumber>2</SegNumber>
                    <ClipGroup>PROGRAMA</ClipGroup>
                    <Description> </Description>
                </Segment>
            </Segments></Clip></XML>