<?xml version="1.0" encoding="UTF-8" ?>        
        <XML>
            <Content>UPDATE</Content>
            <Clip>
                <ClipName>PRCAINF0039</ClipName>
                <TipoContenido>PROMOS CARTELERA</TipoContenido>
                <Contenido><![CDATA[ ESTA MAÑANA: CON NOMBRE DE MUJER - IMPACTO ECONOMICO - CONEXION GLOBAL ]]></Contenido>
                <OriginalTitle></OriginalTitle>
                <Description> </Description>
                <Notes>a</Notes>
                <DurPrev></DurPrev>
                <Chapter></Chapter>
                <EndDate></EndDate>
                <EPG></EPG>
                <EPG_Content> </EPG_Content>
                <Segments>
            
                <Segment>
                    <SegTitle>1-1 CARTELERA INFORMATIVA - ESTA MAÑANA: CON NOMBRE DE MUJER - IMPACTO ECONOMICO - CONEXION GLOBAL </SegTitle>
                    <MediaID>PRCAINF0039</MediaID>
                    <Duration>00:00:10.00</Duration>
                    <SegNumber>1</SegNumber>
                    <ClipGroup>PROMO</ClipGroup>
                    <Description> </Description>
                </Segment>
            </Segments></Clip></XML>