<?xml version="1.0" encoding="UTF-8" ?>        
        <XML>
            <Content>UPDATE</Content>
            <Clip>
                <ClipName>PRCPRET0182</ClipName>
                <TipoContenido>PROMOS CAPITULARES</TipoContenido>
                <Contenido><![CDATA[ RT SUEÑO APLAZADOHOY MIER 09ENE13 21:00HR]]></Contenido>
                <OriginalTitle></OriginalTitle>
                <Description> </Description>
                <Notes>a</Notes>
                <DurPrev></DurPrev>
                <Chapter></Chapter>
                <EndDate></EndDate>
                <EPG></EPG>
                <EPG_Content> </EPG_Content>
                <Segments>
            
                <Segment>
                    <SegTitle>1-1 REPORTAJE TELESUR - RT SUEÑO APLAZADOHOY MIER 09ENE13 21:00HR</SegTitle>
                    <MediaID>PRCPRET0182</MediaID>
                    <Duration>00:00:35.00</Duration>
                    <SegNumber>1</SegNumber>
                    <ClipGroup>PROMO</ClipGroup>
                    <Description> </Description>
                </Segment>
            </Segments></Clip></XML>